bruter/__init__.py
bruter-0.0.2.dist-info/LICENSE
bruter-0.0.2.dist-info/METADATA
bruter-0.0.2.dist-info/WHEEL
bruter-0.0.2.dist-info/top_level.txt
bruter-0.0.2.dist-info/RECORD
