Metadata-Version: 2.1
Name: bruter
Version: 0.0.2
Summary: String bruteforcer
Home-page: https://github.com/sdslabs/bruter
Author: SDSLabs
Author-email: contact@sdslabs.co.in
License: UNKNOWN
Platform: UNKNOWN
Classifier: Programming Language :: Python :: 3
Classifier: Operating System :: OS Independent
Requires-Python: >=3.6
